additional_dist_files/Dockerfile
additional_dist_files/__init__.py
additional_dist_files/docker-compose.yml
additional_dist_files/mongo-init.js
jot_iris-1.20.9.data/scripts/iris.py
listener/__init__.py
listener/auth.py
listener/listener.py
listener/logs_web_socket.py
test_definition_template/__init__.py
test_definition_template/common/__init__.py
test_definition_template/common/common_definitions.py
test_definition_template/common/events.py
test_definition_template/common/init_deinit.py
test_definition_template/common/instruments.py
test_definition_template/common/mongodb_handler.py
test_definition_template/common/test_report_writer.py
test_definition_template/sequences/__init__.py
test_definition_template/sequences/example_sequence/__init__.py
test_definition_template/sequences/example_sequence/first_case.py
test_definition_template/sequences/example_sequence/limits.py
test_definition_template/sequences/example_sequence/second_case.py
test_definition_template/sequences/example_sequence/test_case_parameters.py
test_definition_template/sequences/example_sequence/test_definition.py
test_definition_template/test_case_pool/__init__.py
test_definition_template/test_case_pool/pool_test_case_example.py
test_runner/__init__.py
test_runner/dut.py
test_runner/exceptions.py
test_runner/helpers.py
test_runner/progress_reporter.py
test_runner/runner.py
test_runner/test_case.py
test_runner/test_position.py
ui/__init__.py
ui/build/asset-manifest.json
ui/build/index.html
ui/build/service-worker.js
ui/build/app/favicon.ico
ui/build/app/manifest.json
ui/build/i18n/en/applications.json
ui/build/i18n/en/diagnostics.json
ui/build/i18n/en/home.json
ui/build/i18n/en/login.json
ui/build/i18n/en/main.json
ui/build/i18n/en/manual-usage.json
ui/build/i18n/en/navigation.json
ui/build/i18n/en/robot.json
ui/build/i18n/zh/applications.json
ui/build/i18n/zh/diagnostics.json
ui/build/i18n/zh/login.json
ui/build/i18n/zh/main.json
ui/build/i18n/zh/manual-usage.json
ui/build/i18n/zh/navigation.json
jot_iris-1.20.9.dist-info/LICENSE
jot_iris-1.20.9.dist-info/METADATA
jot_iris-1.20.9.dist-info/WHEEL
jot_iris-1.20.9.dist-info/top_level.txt
jot_iris-1.20.9.dist-info/RECORD
