Metadata-Version: 2.1
Name: jot-iris
Version: 1.20.9
Summary: Super simple test sequencer for production testing
Home-page: https://www.jotautomation.com
Author: JOT Automation Ltd.
Author-email: info@jotautomation.com
License: MIT License
Platform: UNKNOWN
Classifier: Programming Language :: Python :: 3
Classifier: License :: OSI Approved :: MIT License
Classifier: Operating System :: OS Independent
License-File: LICENSE
Requires-Dist: PyYAML
Requires-Dist: bcrypt (==3.2.2)
Requires-Dist: colorama
Requires-Dist: colorlog
Requires-Dist: gaiaclient
Requires-Dist: json2html
Requires-Dist: mock
Requires-Dist: pymongo
Requires-Dist: tornado
Requires-Dist: wheel
